edc_detect_pii.py
edc_detect_pii-0.2.1.dist-info/licenses/LICENSE
edc_detect_pii-0.2.1.dist-info/METADATA
edc_detect_pii-0.2.1.dist-info/WHEEL
edc_detect_pii-0.2.1.dist-info/top_level.txt
edc_detect_pii-0.2.1.dist-info/RECORD
