Metadata-Version: 2.4
Name: edc-detect-pii
Version: 0.2.1
Summary: detect PII in EDC projects
Author-email: Erik van Widenfelt <ew2789@gmail.com>
License-Expression: MIT
Classifier: Environment :: Web Environment
Classifier: Intended Audience :: Developers
Classifier: Operating System :: OS Independent
Classifier: Programming Language :: Python :: 3.12
Classifier: Programming Language :: Python :: 3.13
Requires-Python: >=3.13
License-File: LICENSE
Requires-Dist: nbformat
Requires-Dist: requests
Dynamic: license-file
